vedro_hooks/__init__.py
vedro_hooks/hooks.py
vedro_hooks/py.typed
vedro_hooks/vedro_hooks.py
vedro_hooks-0.3.0.dist-info/LICENSE
vedro_hooks-0.3.0.dist-info/METADATA
vedro_hooks-0.3.0.dist-info/WHEEL
vedro_hooks-0.3.0.dist-info/RECORD
